Metadata-Version: 1.0
Name: jabkabin
Version: 1.1.0
Summary: Full Pastebin API wrapper for python
Home-page: UNKNOWN
Author: UNKNOWN
Author-email: jabka.jaba@yandex.ru
License: UNKNOWN
Platform: UNKNOWN
